ChurchToolsApi/__init__.py
ChurchToolsApi/churchtools_api.py
ChurchToolsApi/exceptions.py
churchtoolsapi-0.0.2rc83.post1.dist-info/LICENSE
churchtoolsapi-0.0.2rc83.post1.dist-info/WHEEL
churchtoolsapi-0.0.2rc83.post1.dist-info/METADATA
churchtoolsapi-0.0.2rc83.post1.dist-info/RECORD
