Metadata-Version: 2.1
Name: ChurchToolsApi
Version: 0.0.2rc83.post1
Summary: A Python wrapper for the ChurchTools API
Author-email: Felix Kotschenreuther <felix.kotschenreuther@gmail.com>
Requires-Python: >=3.8.1
Classifier: Development Status :: 3 - Alpha
Classifier: Intended Audience :: Developers
Classifier: License :: OSI Approved :: MIT License
Classifier: Programming Language :: Python :: 3 :: Only
Classifier: Programming Language :: Python :: 3.8
Classifier: Programming Language :: Python :: 3.9
Classifier: Programming Language :: Python :: 3.10
Classifier: Programming Language :: Python :: 3.11
Requires-Dist: pyspark>=3.0.0 ; extra == "spark"
Requires-Dist: bandit[toml]==1.7.5 ; extra == "test"
Requires-Dist: black==23.3.0 ; extra == "test"
Requires-Dist: check-manifest==0.49 ; extra == "test"
Requires-Dist: flake8-bugbear==23.6.5 ; extra == "test"
Requires-Dist: flake8-docstrings ; extra == "test"
Requires-Dist: flake8-formatter_junit_xml ; extra == "test"
Requires-Dist: flake8 ; extra == "test"
Requires-Dist: flake8-pyproject ; extra == "test"
Requires-Dist: pre-commit==3.3.3 ; extra == "test"
Requires-Dist: pylint==2.17.4 ; extra == "test"
Requires-Dist: pylint_junit ; extra == "test"
Requires-Dist: pytest-cov==4.1.0 ; extra == "test"
Requires-Dist: pytest-mock<3.11.2 ; extra == "test"
Requires-Dist: pytest-runner ; extra == "test"
Requires-Dist: pytest==7.4.0 ; extra == "test"
Requires-Dist: pytest-github-actions-annotate-failures ; extra == "test"
Requires-Dist: shellcheck-py==0.9.0.5 ; extra == "test"
Requires-Dist: responses==0.23.1 ; extra == "test"
Project-URL: Documentation, https://github.com/microsoft/python-package-template/tree/main#readme
Project-URL: Source, https://github.com/microsoft/python-package-template
Project-URL: Tracker, https://github.com/microsoft/python-package-template/issues
Provides-Extra: spark
Provides-Extra: test
